medium_multiply23/__init__.py
medium_multiply23/multiplication.py
medium_multiply23-0.1.0.dist-info/METADATA
medium_multiply23-0.1.0.dist-info/WHEEL
medium_multiply23-0.1.0.dist-info/top_level.txt
medium_multiply23-0.1.0.dist-info/RECORD
